pasters/__init__.py
pasters/main.py
pasters-1.0.0.dist-info/licenses/LICENSE
pasters-1.0.0.dist-info/METADATA
pasters-1.0.0.dist-info/WHEEL
pasters-1.0.0.dist-info/top_level.txt
pasters-1.0.0.dist-info/RECORD
